pyalgotrade_mootdx/__init__.py
pyalgotrade_mootdx/barfeed.py
pyalgotrade_mootdx/broker.py
pyalgotrade_mootdx/common.py
pyalgotrade_mootdx/livefeed.py
pyalgotrade_mootdx/tools.py
pyalgotrade_mootdx-0.1.1.dist-info/METADATA
pyalgotrade_mootdx-0.1.1.dist-info/RECORD
pyalgotrade_mootdx-0.1.1.dist-info/WHEEL
pyalgotrade_mootdx-0.1.1.dist-info/top_level.txt
