Metadata-Version: 2.1
Name: pyalgotrade-mootdx
Version: 0.1.1
Summary: pyalgotrade mootdx module
Home-page: https://github.com/bopo/pyalgotrade_mootdx
Author: bopo.wang
Author-email: ibopo@126.com
License: MIT license
Keywords: pyalgotrade_mootdx
Platform: UNKNOWN
Classifier: Development Status :: 2 - Pre-Alpha
Classifier: Intended Audience :: Developers
Classifier: License :: OSI Approved :: MIT License
Classifier: Natural Language :: English
Classifier: Programming Language :: Python :: 3
Classifier: Programming Language :: Python :: 3.3
Classifier: Programming Language :: Python :: 3.4
Classifier: Programming Language :: Python :: 3.5
Classifier: Programming Language :: Python :: 3.6
Classifier: Programming Language :: Python :: 3.7
Requires-Dist: pyalgotrade
Requires-Dist: mootdx
